chipdb_upload/__init__.py
chipdb_upload/data_upload.py
ggr_cwl_ipynb_gen-0.5.1.data/data/templates/cwl_json_gen.j2
ggr_cwl_ipynb_gen-0.5.1.data/data/templates/cwl_slurm_array_gen.j2
ggr_cwl_ipynb_gen-0.5.1.data/data/templates/data_upload.j2
ggr_cwl_ipynb_gen-0.5.1.data/data/templates/download_fastq_files.j2
ggr_cwl_ipynb_gen-0.5.1.data/data/templates/generate_plots.j2
ggr_cwl_ipynb_gen-0.5.1.data/data/templates/generate_qc_cell.j2
ggr_cwl_ipynb_gen-0.5.1.data/data/templates/merge_lanes_fastq.j2
ggr_cwl_ipynb_gen-0.5.1.data/data/templates/ungzip_fastq_files.j2
ggr_cwl_ipynb_gen-0.5.1.data/scripts/chipdb_data_upload
ggr_cwl_ipynb_gen-0.5.1.data/scripts/ggr_cwl_ipynb_gen
ipynb_gen/__init__.py
ipynb_gen/consts.py
ipynb_gen/main.py
ipynb_gen/templates/cwl_json_gen.j2
ipynb_gen/templates/cwl_slurm_array_gen.j2
ipynb_gen/templates/data_upload.j2
ipynb_gen/templates/download_fastq_files.j2
ipynb_gen/templates/generate_plots.j2
ipynb_gen/templates/generate_qc_cell.j2
ipynb_gen/templates/merge_lanes_fastq.j2
ipynb_gen/templates/ungzip_fastq_files.j2
ggr_cwl_ipynb_gen-0.5.1.dist-info/LICENSE
ggr_cwl_ipynb_gen-0.5.1.dist-info/METADATA
ggr_cwl_ipynb_gen-0.5.1.dist-info/WHEEL
ggr_cwl_ipynb_gen-0.5.1.dist-info/top_level.txt
ggr_cwl_ipynb_gen-0.5.1.dist-info/RECORD
