Metadata-Version: 2.1
Name: ggr-cwl-ipynb-gen
Version: 0.5.1
Summary: IPython notebook generator for GGR CWL processing pipelines of genomic data
Home-page: https://github.com/ReddyLab/ggr-cwl-ipynb-gen
Author: Alejandro Barrera
Author-email: alejandro.barrera@duke.edu
Project-URL: Bug Tracker, https://github.com/ReddyLab/ggr-cwl-ipynb-gen/issues
Project-URL: Source, https://github.com/ReddyLab/ggr-cwl-ipynb-gen/
Keywords: cwl,bioinformatics,development
Classifier: Development Status :: 3 - Alpha
Classifier: Intended Audience :: Science/Research
Classifier: Topic :: Scientific/Engineering :: Bio-Informatics
Classifier: License :: OSI Approved :: MIT License
Classifier: Programming Language :: Python :: 3
Classifier: Programming Language :: Python :: 3.6
Classifier: Programming Language :: Python :: 3.7
Classifier: Programming Language :: Python :: 3.8
Classifier: Programming Language :: Python :: 3.9
Requires-Python: >=3.1
License-File: LICENSE
Requires-Dist: jinja2>=2.8
Requires-Dist: nbformat>=4.0.1
Requires-Dist: numpy>=1.10.4
Requires-Dist: pandas>=0.17.1
Requires-Dist: xlrd>=1.0.0
Requires-Dist: ruamel.yaml>=0.11.11
Requires-Dist: pymongo>=3.4.0
